Workbook

Sheet Instrucciones
B2: Plantilla MACD(12, 26, 9) con medias simples y exponenciales
B4: Qué editar | C4: Solo las celdas con fondo amarillo y texto azul: fechas y cierres en la hoja Datos, y los tres periodos en la parte superior de MACD_EMA (valen para todo el libro).
B5: Datos de ejemplo | C5: La hoja Datos trae una serie SINTÉTICA generada al azar (104 viernes). No es ninguna emisora real. Reemplázala con tus cierres antes de entregar.
B6: Cómo pegar tus datos | C6: Pega fechas en Datos!A2 hacia abajo y cierres en Datos!B2 hacia abajo, del más antiguo al más reciente. Semanal = cierre del viernes; mensual = último cierre del mes.
B7: Si tienes otro número de filas | C7: Las hojas de cálculo tienen 104 filas (9 a 112). Si pegas más, selecciona la última fila de cada hoja y arrástrala hacia abajo. Si pegas menos, borra las filas sobrantes. Después ajusta el rango de las gráficas (clic derecho > Seleccionar datos).
B8: MACD_EMA | C8: Versión estándar: EMA con alfa = 2/(N+1), semilla = SMA de los primeros N valores. MACD = EMA12 - EMA26; Señal = EMA9 del MACD; Histograma = MACD - Señal.
B9: MACD_SMA | C9: Misma cuenta con medias simples (variante permitida en clase; útil para comparar).
B10: RSI | C10: RSI(14) como se hizo en clase (promedios simples de 14 cambios) y con el suavizado de Wilder.
B11: Ejemplo_a_mano | C11: MACD(3, 6, 3) sobre 12 precios pequeños para seguir cada paso con calculadora.
B12: Graficas | C12: Precio con las dos EMA y panel MACD/Señal/Histograma de los últimos 26 periodos (filas 87 a 112).
B13: Primeros valores | C13: Con 12/26/9: la EMA12 aparece en t=12, la EMA26 y el MACD en t=26, la señal y el histograma en t=34. Por eso se necesita más historia que los 26 periodos que se reportan.
B14: Separador de argumentos | C14: Las fórmulas se guardan en formato interno; Excel las muestra con los nombres y separadores de tu idioma (en español de México: SI, PROMEDIO, Y, O, INDICE, con coma).
B15: Nombres definidos | C15: N_rap, N_len, N_sen, a_rap, a_len, a_sen y N_rsi apuntan a las celdas de parámetros. Se ven en Fórmulas > Administrador de nombres.
... B17: Aviso | C17: Material académico del diplomado; no es recomendación de inversión.

Sheet Datos
A1: Fecha | B1: Cierre | D1: SERIE SINTÉTICA DE EJEMPLO: reemplazar con cierres reales (del más antiguo al más reciente).
A2: 45555 | B2: 167.72 | D2: Fuente de tus datos: | E2: [Yahoo Finance / Investing / WSJ, ticker, fecha de descarga]
A3: 45562 | B3: 172.28 | D3: Frecuencia: | E3: Semanal (cierre del viernes)
A4: 45569 | B4: 167.83
A5: 45576 | B5: 165.21
A6: 45583 | B6: 162.76
A7: 45590 | B7: 165.13
A8: 45597 | B8: 165.35
A9: 45604 | B9: 161.85
A10: 45611 | B10: 165.48
A11: 45618 | B11: 162.15
A12: 45625 | B12: 166.72
A13: 45632 | B13: 162.27
A14: 45639 | B14: 158.8
A15: 45646 | B15: 164.42
... A105: 46276 | B105: 218.77

Sheet MACD_EMA
A1: MACD con medias móviles exponenciales
B2: Parámetro | C2: N | D2: alfa = 2/(N+1)
B3: Periodo EMA rápida | C3: 12 | D3: =2/(C3+1) -> 0.15384615 | F3: Primer MACD en t = | G3: =N_len -> 26 | I3: En tendencia de pendiente m constante: MACD tiende a (G6 - G5) * m = 7 m.
B4: Periodo EMA lenta | C4: 26 | D4: =2/(C4+1) -> 0.074074074 | F4: Primera señal en t = | G4: =N_len+N_sen-1 -> 34
B5: Periodo línea de señal | C5: 9 | D5: =2/(C5+1) -> 0.2 | F5: Retraso EMA rápida (N-1)/2 = | G5: =(N_rap-1)/2 -> 5.5
F6: Retraso EMA lenta (N-1)/2 = | G6: =(N_len-1)/2 -> 12.5
A8: t | B8: Fecha | C8: Cierre | D8: EMA rápida | E8: EMA lenta | F8: MACD | G8: Señal | H8: Histograma | I8: Cruce MACD/Señal | J8: MACD vs cero | K8: EMAs se acercan o separan | L8: PPO (MACD / EMA lenta)
A9: =ROW()-8 -> 1 | B9: =Datos!A2 -> 45555 | C9: =Datos!B2 -> 167.72 | D9: =IF(A9<N_rap,"",IF(A9=N_rap,AVERAGE($C$9:C9),a_rap*C9+(1-a_rap)*D8)) | E9: =IF(A9<N_len,"",IF(A9=N_len,AVERAGE($C$9:C9),a_len*C9+(1-a_len)*E8)) | F9: =IF(E9="","",D9-E9) | G9: =IF(A9<N_len+N_sen-1,"",IF(A9=N_len+N_sen-1,AVERAGE($F$9:F9),a_sen*F9+(1-a_sen)*G8)) | H9: =IF(G9="","",F9-G9) | I9: =IF(OR(H9="",H8=""),"",IF(AND(H8<=0,H9>0),"Cruce alcista",IF(AND(H8>=0,H9<0),"Cruce bajista",""))) | J9: =IF(F9="","",IF(F9>0,"Arriba de 0","Debajo de 0")) | K9: =IF(OR(F9="",F8=""),"",IF(ABS(F9)<ABS(F8),"Convergen","Divergen")) | L9: =IF(F9="","",F9/E9)
A10: =ROW()-8 -> 2 | B10: =Datos!A3 -> 45562 | C10: =Datos!B3 -> 172.28 | D10: =IF(A10<N_rap,"",IF(A10=N_rap,AVERAGE($C$9:C10),a_rap*C10+(1-a_rap)*D9)) | E10: =IF(A10<N_len,"",IF(A10=N_len,AVERAGE($C$9:C10),a_len*C10+(1-a_len)*E9)) | F10: =IF(E10="","",D10-E10) | G10: =IF(A10<N_len+N_sen-1,"",IF(A10=N_len+N_sen-1,AVERAGE($F$9:F10),a_sen*F10+(1-a_sen)*G9)) | H10: =IF(G10="","",F10-G10) | I10: =IF(OR(H10="",H9=""),"",IF(AND(H9<=0,H10>0),"Cruce alcista",IF(AND(H9>=0,H10<0),"Cruce bajista",""))) | J10: =IF(F10="","",IF(F10>0,"Arriba de 0","Debajo de 0")) | K10: =IF(OR(F10="",F9=""),"",IF(ABS(F10)<ABS(F9),"Convergen","Divergen")) | L10: =IF(F10="","",F10/E10)
A11: =ROW()-8 -> 3 | B11: =Datos!A4 -> 45569 | C11: =Datos!B4 -> 167.83 | D11: =IF(A11<N_rap,"",IF(A11=N_rap,AVERAGE($C$9:C11),a_rap*C11+(1-a_rap)*D10)) | E11: =IF(A11<N_len,"",IF(A11=N_len,AVERAGE($C$9:C11),a_len*C11+(1-a_len)*E10)) | F11: =IF(E11="","",D11-E11) | G11: =IF(A11<N_len+N_sen-1,"",IF(A11=N_len+N_sen-1,AVERAGE($F$9:F11),a_sen*F11+(1-a_sen)*G10)) | H11: =IF(G11="","",F11-G11) | I11: =IF(OR(H11="",H10=""),"",IF(AND(H10<=0,H11>0),"Cruce alcista",IF(AND(H10>=0,H11<0),"Cruce bajista",""))) | J11: =IF(F11="","",IF(F11>0,"Arriba de 0","Debajo de 0")) | K11: =IF(OR(F11="",F10=""),"",IF(ABS(F11)<ABS(F10),"Convergen","Divergen")) | L11: =IF(F11="","",F11/E11)
A12: =ROW()-8 -> 4 | B12: =Datos!A5 -> 45576 | C12: =Datos!B5 -> 165.21 | D12: =IF(A12<N_rap,"",IF(A12=N_rap,AVERAGE($C$9:C12),a_rap*C12+(1-a_rap)*D11)) | E12: =IF(A12<N_len,"",IF(A12=N_len,AVERAGE($C$9:C12),a_len*C12+(1-a_len)*E11)) | F12: =IF(E12="","",D12-E12) | G12: =IF(A12<N_len+N_sen-1,"",IF(A12=N_len+N_sen-1,AVERAGE($F$9:F12),a_sen*F12+(1-a_sen)*G11)) | H12: =IF(G12="","",F12-G12) | I12: =IF(OR(H12="",H11=""),"",IF(AND(H11<=0,H12>0),"Cruce alcista",IF(AND(H11>=0,H12<0),"Cruce bajista",""))) | J12: =IF(F12="","",IF(F12>0,"Arriba de 0","Debajo de 0")) | K12: =IF(OR(F12="",F11=""),"",IF(ABS(F12)<ABS(F11),"Convergen","Divergen")) | L12: =IF(F12="","",F12/E12)
A13: =ROW()-8 -> 5 | B13: =Datos!A6 -> 45583 | C13: =Datos!B6 -> 162.76 | D13: =IF(A13<N_rap,"",IF(A13=N_rap,AVERAGE($C$9:C13),a_rap*C13+(1-a_rap)*D12)) | E13: =IF(A13<N_len,"",IF(A13=N_len,AVERAGE($C$9:C13),a_len*C13+(1-a_len)*E12)) | F13: =IF(E13="","",D13-E13) | G13: =IF(A13<N_len+N_sen-1,"",IF(A13=N_len+N_sen-1,AVERAGE($F$9:F13),a_sen*F13+(1-a_sen)*G12)) | H13: =IF(G13="","",F13-G13) | I13: =IF(OR(H13="",H12=""),"",IF(AND(H12<=0,H13>0),"Cruce alcista",IF(AND(H12>=0,H13<0),"Cruce bajista",""))) | J13: =IF(F13="","",IF(F13>0,"Arriba de 0","Debajo de 0")) | K13: =IF(OR(F13="",F12=""),"",IF(ABS(F13)<ABS(F12),"Convergen","Divergen")) | L13: =IF(F13="","",F13/E13)
A14: =ROW()-8 -> 6 | B14: =Datos!A7 -> 45590 | C14: =Datos!B7 -> 165.13 | D14: =IF(A14<N_rap,"",IF(A14=N_rap,AVERAGE($C$9:C14),a_rap*C14+(1-a_rap)*D13)) | E14: =IF(A14<N_len,"",IF(A14=N_len,AVERAGE($C$9:C14),a_len*C14+(1-a_len)*E13)) | F14: =IF(E14="","",D14-E14) | G14: =IF(A14<N_len+N_sen-1,"",IF(A14=N_len+N_sen-1,AVERAGE($F$9:F14),a_sen*F14+(1-a_sen)*G13)) | H14: =IF(G14="","",F14-G14) | I14: =IF(OR(H14="",H13=""),"",IF(AND(H13<=0,H14>0),"Cruce alcista",IF(AND(H13>=0,H14<0),"Cruce bajista",""))) | J14: =IF(F14="","",IF(F14>0,"Arriba de 0","Debajo de 0")) | K14: =IF(OR(F14="",F13=""),"",IF(ABS(F14)<ABS(F13),"Convergen","Divergen")) | L14: =IF(F14="","",F14/E14)
A15: =ROW()-8 -> 7 | B15: =Datos!A8 -> 45597 | C15: =Datos!B8 -> 165.35 | D15: =IF(A15<N_rap,"",IF(A15=N_rap,AVERAGE($C$9:C15),a_rap*C15+(1-a_rap)*D14)) | E15: =IF(A15<N_len,"",IF(A15=N_len,AVERAGE($C$9:C15),a_len*C15+(1-a_len)*E14)) | F15: =IF(E15="","",D15-E15) | G15: =IF(A15<N_len+N_sen-1,"",IF(A15=N_len+N_sen-1,AVERAGE($F$9:F15),a_sen*F15+(1-a_sen)*G14)) | H15: =IF(G15="","",F15-G15) | I15: =IF(OR(H15="",H14=""),"",IF(AND(H14<=0,H15>0),"Cruce alcista",IF(AND(H14>=0,H15<0),"Cruce bajista",""))) | J15: =IF(F15="","",IF(F15>0,"Arriba de 0","Debajo de 0")) | K15: =IF(OR(F15="",F14=""),"",IF(ABS(F15)<ABS(F14),"Convergen","Divergen")) | L15: =IF(F15="","",F15/E15)
A16: =ROW()-8 -> 8 | B16: =Datos!A9 -> 45604 | C16: =Datos!B9 -> 161.85 | D16: =IF(A16<N_rap,"",IF(A16=N_rap,AVERAGE($C$9:C16),a_rap*C16+(1-a_rap)*D15)) | E16: =IF(A16<N_len,"",IF(A16=N_len,AVERAGE($C$9:C16),a_len*C16+(1-a_len)*E15)) | F16: =IF(E16="","",D16-E16) | G16: =IF(A16<N_len+N_sen-1,"",IF(A16=N_len+N_sen-1,AVERAGE($F$9:F16),a_sen*F16+(1-a_sen)*G15)) | H16: =IF(G16="","",F16-G16) | I16: =IF(OR(H16="",H15=""),"",IF(AND(H15<=0,H16>0),"Cruce alcista",IF(AND(H15>=0,H16<0),"Cruce bajista",""))) | J16: =IF(F16="","",IF(F16>0,"Arriba de 0","Debajo de 0")) | K16: =IF(OR(F16="",F15=""),"",IF(ABS(F16)<ABS(F15),"Convergen","Divergen")) | L16: =IF(F16="","",F16/E16)
A17: =ROW()-8 -> 9 | B17: =Datos!A10 -> 45611 | C17: =Datos!B10 -> 165.48 | D17: =IF(A17<N_rap,"",IF(A17=N_rap,AVERAGE($C$9:C17),a_rap*C17+(1-a_rap)*D16)) | E17: =IF(A17<N_len,"",IF(A17=N_len,AVERAGE($C$9:C17),a_len*C17+(1-a_len)*E16)) | F17: =IF(E17="","",D17-E17) | G17: =IF(A17<N_len+N_sen-1,"",IF(A17=N_len+N_sen-1,AVERAGE($F$9:F17),a_sen*F17+(1-a_sen)*G16)) | H17: =IF(G17="","",F17-G17) | I17: =IF(OR(H17="",H16=""),"",IF(AND(H16<=0,H17>0),"Cruce alcista",IF(AND(H16>=0,H17<0),"Cruce bajista",""))) | J17: =IF(F17="","",IF(F17>0,"Arriba de 0","Debajo de 0")) | K17: =IF(OR(F17="",F16=""),"",IF(ABS(F17)<ABS(F16),"Convergen","Divergen")) | L17: =IF(F17="","",F17/E17)
A18: =ROW()-8 -> 10 | B18: =Datos!A11 -> 45618 | C18: =Datos!B11 -> 162.15 | D18: =IF(A18<N_rap,"",IF(A18=N_rap,AVERAGE($C$9:C18),a_rap*C18+(1-a_rap)*D17)) | E18: =IF(A18<N_len,"",IF(A18=N_len,AVERAGE($C$9:C18),a_len*C18+(1-a_len)*E17)) | F18: =IF(E18="","",D18-E18) | G18: =IF(A18<N_len+N_sen-1,"",IF(A18=N_len+N_sen-1,AVERAGE($F$9:F18),a_sen*F18+(1-a_sen)*G17)) | H18: =IF(G18="","",F18-G18) | I18: =IF(OR(H18="",H17=""),"",IF(AND(H17<=0,H18>0),"Cruce alcista",IF(AND(H17>=0,H18<0),"Cruce bajista",""))) | J18: =IF(F18="","",IF(F18>0,"Arriba de 0","Debajo de 0")) | K18: =IF(OR(F18="",F17=""),"",IF(ABS(F18)<ABS(F17),"Convergen","Divergen")) | L18: =IF(F18="","",F18/E18)
A19: =ROW()-8 -> 11 | B19: =Datos!A12 -> 45625 | C19: =Datos!B12 -> 166.72 | D19: =IF(A19<N_rap,"",IF(A19=N_rap,AVERAGE($C$9:C19),a_rap*C19+(1-a_rap)*D18)) | E19: =IF(A19<N_len,"",IF(A19=N_len,AVERAGE($C$9:C19),a_len*C19+(1-a_len)*E18)) | F19: =IF(E19="","",D19-E19) | G19: =IF(A19<N_len+N_sen-1,"",IF(A19=N_len+N_sen-1,AVERAGE($F$9:F19),a_sen*F19+(1-a_sen)*G18)) | H19: =IF(G19="","",F19-G19) | I19: =IF(OR(H19="",H18=""),"",IF(AND(H18<=0,H19>0),"Cruce alcista",IF(AND(H18>=0,H19<0),"Cruce bajista",""))) | J19: =IF(F19="","",IF(F19>0,"Arriba de 0","Debajo de 0")) | K19: =IF(OR(F19="",F18=""),"",IF(ABS(F19)<ABS(F18),"Convergen","Divergen")) | L19: =IF(F19="","",F19/E19)
A20: =ROW()-8 -> 12 | B20: =Datos!A13 -> 45632 | C20: =Datos!B13 -> 162.27 | D20: =IF(A20<N_rap,"",IF(A20=N_rap,AVERAGE($C$9:C20),a_rap*C20+(1-a_rap)*D19)) -> 165.39583 | E20: =IF(A20<N_len,"",IF(A20=N_len,AVERAGE($C$9:C20),a_len*C20+(1-a_len)*E19)) | F20: =IF(E20="","",D20-E20) | G20: =IF(A20<N_len+N_sen-1,"",IF(A20=N_len+N_sen-1,AVERAGE($F$9:F20),a_sen*F20+(1-a_sen)*G19)) | H20: =IF(G20="","",F20-G20) | I20: =IF(OR(H20="",H19=""),"",IF(AND(H19<=0,H20>0),"Cruce alcista",IF(AND(H19>=0,H20<0),"Cruce bajista",""))) | J20: =IF(F20="","",IF(F20>0,"Arriba de 0","Debajo de 0")) | K20: =IF(OR(F20="",F19=""),"",IF(ABS(F20)<ABS(F19),"Convergen","Divergen")) | L20: =IF(F20="","",F20/E20)
... A112: =ROW()-8 -> 104 | B112: =Datos!A105 -> 46276 | C112: =Datos!B105 -> 218.77 | D112: =IF(A112<N_rap,"",IF(A112=N_rap,AVERAGE($C$9:C112),a_rap*C112+(1-a_rap)*D111)) -> 213.11972 | E112: =IF(A112<N_len,"",IF(A112=N_len,AVERAGE($C$9:C112),a_len*C112+(1-a_len)*E111)) -> 217.96577 | F112: =IF(E112="","",D112-E112) -> -4.8460561 | G112: =IF(A112<N_len+N_sen-1,"",IF(A112=N_len+N_sen-1,AVERAGE($F$9:F112),a_sen*F112+(1-a_sen)*G111)) -> -4.4202065 | H112: =IF(G112="","",F112-G112) -> -0.4258496 | I112: =IF(OR(H112="",H111=""),"",IF(AND(H111<=0,H112>0),"Cruce alcista",IF(AND(H111>=0,H112<0),"Cruce bajista",""))) | J112: =IF(F112="","",IF(F112>0,"Arriba de 0","Debajo de 0")) -> Debajo de 0 | K112: =IF(OR(F112="",F111=""),"",IF(ABS(F112)<ABS(F111),"Convergen","Divergen")) -> Convergen | L112: =IF(F112="","",F112/E112) -> -0.022233106

Sheet MACD_SMA
A1: MACD con medias móviles simples (variante para comparar)
B3: Usa los mismos periodos que MACD_EMA (N_rap, N_len, N_sen).
B4: SMA de N en la fila r = PROMEDIO de las N filas que terminan en r (INDICE arma el inicio del rango).
A8: t | B8: Fecha | C8: Cierre | D8: SMA rápida | E8: SMA lenta | F8: MACD (SMA) | G8: Señal (SMA) | H8: Histograma | I8: Cruce MACD/Señal | J8: MACD(SMA) - MACD(EMA)
A9: =ROW()-8 -> 1 | B9: =Datos!A2 -> 45555 | C9: =Datos!B2 -> 167.72 | D9: =IF(A9<N_rap,"",AVERAGE(INDEX($C$9:$C$112,A9-N_rap+1):C9)) | E9: =IF(A9<N_len,"",AVERAGE(INDEX($C$9:$C$112,A9-N_len+1):C9)) | F9: =IF(E9="","",D9-E9) | G9: =IF(A9<N_len+N_sen-1,"",AVERAGE(INDEX($F$9:$F$112,A9-N_sen+1):F9)) | H9: =IF(G9="","",F9-G9) | I9: =IF(OR(H9="",H8=""),"",IF(AND(H8<=0,H9>0),"Cruce alcista",IF(AND(H8>=0,H9<0),"Cruce bajista",""))) | J9: =IF(OR(F9="",MACD_EMA!F9=""),"",F9-MACD_EMA!F9)
A10: =ROW()-8 -> 2 | B10: =Datos!A3 -> 45562 | C10: =Datos!B3 -> 172.28 | D10: =IF(A10<N_rap,"",AVERAGE(INDEX($C$9:$C$112,A10-N_rap+1):C10)) | E10: =IF(A10<N_len,"",AVERAGE(INDEX($C$9:$C$112,A10-N_len+1):C10)) | F10: =IF(E10="","",D10-E10) | G10: =IF(A10<N_len+N_sen-1,"",AVERAGE(INDEX($F$9:$F$112,A10-N_sen+1):F10)) | H10: =IF(G10="","",F10-G10) | I10: =IF(OR(H10="",H9=""),"",IF(AND(H9<=0,H10>0),"Cruce alcista",IF(AND(H9>=0,H10<0),"Cruce bajista",""))) | J10: =IF(OR(F10="",MACD_EMA!F10=""),"",F10-MACD_EMA!F10)
A11: =ROW()-8 -> 3 | B11: =Datos!A4 -> 45569 | C11: =Datos!B4 -> 167.83 | D11: =IF(A11<N_rap,"",AVERAGE(INDEX($C$9:$C$112,A11-N_rap+1):C11)) | E11: =IF(A11<N_len,"",AVERAGE(INDEX($C$9:$C$112,A11-N_len+1):C11)) | F11: =IF(E11="","",D11-E11) | G11: =IF(A11<N_len+N_sen-1,"",AVERAGE(INDEX($F$9:$F$112,A11-N_sen+1):F11)) | H11: =IF(G11="","",F11-G11) | I11: =IF(OR(H11="",H10=""),"",IF(AND(H10<=0,H11>0),"Cruce alcista",IF(AND(H10>=0,H11<0),"Cruce bajista",""))) | J11: =IF(OR(F11="",MACD_EMA!F11=""),"",F11-MACD_EMA!F11)
A12: =ROW()-8 -> 4 | B12: =Datos!A5 -> 45576 | C12: =Datos!B5 -> 165.21 | D12: =IF(A12<N_rap,"",AVERAGE(INDEX($C$9:$C$112,A12-N_rap+1):C12)) | E12: =IF(A12<N_len,"",AVERAGE(INDEX($C$9:$C$112,A12-N_len+1):C12)) | F12: =IF(E12="","",D12-E12) | G12: =IF(A12<N_len+N_sen-1,"",AVERAGE(INDEX($F$9:$F$112,A12-N_sen+1):F12)) | H12: =IF(G12="","",F12-G12) | I12: =IF(OR(H12="",H11=""),"",IF(AND(H11<=0,H12>0),"Cruce alcista",IF(AND(H11>=0,H12<0),"Cruce bajista",""))) | J12: =IF(OR(F12="",MACD_EMA!F12=""),"",F12-MACD_EMA!F12)
A13: =ROW()-8 -> 5 | B13: =Datos!A6 -> 45583 | C13: =Datos!B6 -> 162.76 | D13: =IF(A13<N_rap,"",AVERAGE(INDEX($C$9:$C$112,A13-N_rap+1):C13)) | E13: =IF(A13<N_len,"",AVERAGE(INDEX($C$9:$C$112,A13-N_len+1):C13)) | F13: =IF(E13="","",D13-E13) | G13: =IF(A13<N_len+N_sen-1,"",AVERAGE(INDEX($F$9:$F$112,A13-N_sen+1):F13)) | H13: =IF(G13="","",F13-G13) | I13: =IF(OR(H13="",H12=""),"",IF(AND(H12<=0,H13>0),"Cruce alcista",IF(AND(H12>=0,H13<0),"Cruce bajista",""))) | J13: =IF(OR(F13="",MACD_EMA!F13=""),"",F13-MACD_EMA!F13)
A14: =ROW()-8 -> 6 | B14: =Datos!A7 -> 45590 | C14: =Datos!B7 -> 165.13 | D14: =IF(A14<N_rap,"",AVERAGE(INDEX($C$9:$C$112,A14-N_rap+1):C14)) | E14: =IF(A14<N_len,"",AVERAGE(INDEX($C$9:$C$112,A14-N_len+1):C14)) | F14: =IF(E14="","",D14-E14) | G14: =IF(A14<N_len+N_sen-1,"",AVERAGE(INDEX($F$9:$F$112,A14-N_sen+1):F14)) | H14: =IF(G14="","",F14-G14) | I14: =IF(OR(H14="",H13=""),"",IF(AND(H13<=0,H14>0),"Cruce alcista",IF(AND(H13>=0,H14<0),"Cruce bajista",""))) | J14: =IF(OR(F14="",MACD_EMA!F14=""),"",F14-MACD_EMA!F14)
A15: =ROW()-8 -> 7 | B15: =Datos!A8 -> 45597 | C15: =Datos!B8 -> 165.35 | D15: =IF(A15<N_rap,"",AVERAGE(INDEX($C$9:$C$112,A15-N_rap+1):C15)) | E15: =IF(A15<N_len,"",AVERAGE(INDEX($C$9:$C$112,A15-N_len+1):C15)) | F15: =IF(E15="","",D15-E15) | G15: =IF(A15<N_len+N_sen-1,"",AVERAGE(INDEX($F$9:$F$112,A15-N_sen+1):F15)) | H15: =IF(G15="","",F15-G15) | I15: =IF(OR(H15="",H14=""),"",IF(AND(H14<=0,H15>0),"Cruce alcista",IF(AND(H14>=0,H15<0),"Cruce bajista",""))) | J15: =IF(OR(F15="",MACD_EMA!F15=""),"",F15-MACD_EMA!F15)
A16: =ROW()-8 -> 8 | B16: =Datos!A9 -> 45604 | C16: =Datos!B9 -> 161.85 | D16: =IF(A16<N_rap,"",AVERAGE(INDEX($C$9:$C$112,A16-N_rap+1):C16)) | E16: =IF(A16<N_len,"",AVERAGE(INDEX($C$9:$C$112,A16-N_len+1):C16)) | F16: =IF(E16="","",D16-E16) | G16: =IF(A16<N_len+N_sen-1,"",AVERAGE(INDEX($F$9:$F$112,A16-N_sen+1):F16)) | H16: =IF(G16="","",F16-G16) | I16: =IF(OR(H16="",H15=""),"",IF(AND(H15<=0,H16>0),"Cruce alcista",IF(AND(H15>=0,H16<0),"Cruce bajista",""))) | J16: =IF(OR(F16="",MACD_EMA!F16=""),"",F16-MACD_EMA!F16)
A17: =ROW()-8 -> 9 | B17: =Datos!A10 -> 45611 | C17: =Datos!B10 -> 165.48 | D17: =IF(A17<N_rap,"",AVERAGE(INDEX($C$9:$C$112,A17-N_rap+1):C17)) | E17: =IF(A17<N_len,"",AVERAGE(INDEX($C$9:$C$112,A17-N_len+1):C17)) | F17: =IF(E17="","",D17-E17) | G17: =IF(A17<N_len+N_sen-1,"",AVERAGE(INDEX($F$9:$F$112,A17-N_sen+1):F17)) | H17: =IF(G17="","",F17-G17) | I17: =IF(OR(H17="",H16=""),"",IF(AND(H16<=0,H17>0),"Cruce alcista",IF(AND(H16>=0,H17<0),"Cruce bajista",""))) | J17: =IF(OR(F17="",MACD_EMA!F17=""),"",F17-MACD_EMA!F17)
A18: =ROW()-8 -> 10 | B18: =Datos!A11 -> 45618 | C18: =Datos!B11 -> 162.15 | D18: =IF(A18<N_rap,"",AVERAGE(INDEX($C$9:$C$112,A18-N_rap+1):C18)) | E18: =IF(A18<N_len,"",AVERAGE(INDEX($C$9:$C$112,A18-N_len+1):C18)) | F18: =IF(E18="","",D18-E18) | G18: =IF(A18<N_len+N_sen-1,"",AVERAGE(INDEX($F$9:$F$112,A18-N_sen+1):F18)) | H18: =IF(G18="","",F18-G18) | I18: =IF(OR(H18="",H17=""),"",IF(AND(H17<=0,H18>0),"Cruce alcista",IF(AND(H17>=0,H18<0),"Cruce bajista",""))) | J18: =IF(OR(F18="",MACD_EMA!F18=""),"",F18-MACD_EMA!F18)
A19: =ROW()-8 -> 11 | B19: =Datos!A12 -> 45625 | C19: =Datos!B12 -> 166.72 | D19: =IF(A19<N_rap,"",AVERAGE(INDEX($C$9:$C$112,A19-N_rap+1):C19)) | E19: =IF(A19<N_len,"",AVERAGE(INDEX($C$9:$C$112,A19-N_len+1):C19)) | F19: =IF(E19="","",D19-E19) | G19: =IF(A19<N_len+N_sen-1,"",AVERAGE(INDEX($F$9:$F$112,A19-N_sen+1):F19)) | H19: =IF(G19="","",F19-G19) | I19: =IF(OR(H19="",H18=""),"",IF(AND(H18<=0,H19>0),"Cruce alcista",IF(AND(H18>=0,H19<0),"Cruce bajista",""))) | J19: =IF(OR(F19="",MACD_EMA!F19=""),"",F19-MACD_EMA!F19)
A20: =ROW()-8 -> 12 | B20: =Datos!A13 -> 45632 | C20: =Datos!B13 -> 162.27 | D20: =IF(A20<N_rap,"",AVERAGE(INDEX($C$9:$C$112,A20-N_rap+1):C20)) -> 165.39583 | E20: =IF(A20<N_len,"",AVERAGE(INDEX($C$9:$C$112,A20-N_len+1):C20)) | F20: =IF(E20="","",D20-E20) | G20: =IF(A20<N_len+N_sen-1,"",AVERAGE(INDEX($F$9:$F$112,A20-N_sen+1):F20)) | H20: =IF(G20="","",F20-G20) | I20: =IF(OR(H20="",H19=""),"",IF(AND(H19<=0,H20>0),"Cruce alcista",IF(AND(H19>=0,H20<0),"Cruce bajista",""))) | J20: =IF(OR(F20="",MACD_EMA!F20=""),"",F20-MACD_EMA!F20)
... A112: =ROW()-8 -> 104 | B112: =Datos!A105 -> 46276 | C112: =Datos!B105 -> 218.77 | D112: =IF(A112<N_rap,"",AVERAGE(INDEX($C$9:$C$112,A112-N_rap+1):C112)) -> 212.82167 | E112: =IF(A112<N_len,"",AVERAGE(INDEX($C$9:$C$112,A112-N_len+1):C112)) -> 221.66385 | F112: =IF(E112="","",D112-E112) -> -8.8421795 | G112: =IF(A112<N_len+N_sen-1,"",AVERAGE(INDEX($F$9:$F$112,A112-N_sen+1):F112)) -> -8.4477849 | H112: =IF(G112="","",F112-G112) -> -0.39439459 | I112: =IF(OR(H112="",H111=""),"",IF(AND(H111<=0,H112>0),"Cruce alcista",IF(AND(H111>=0,H112<0),"Cruce bajista",""))) | J112: =IF(OR(F112="",MACD_EMA!F112=""),"",F112-MACD_EMA!F112) -> -3.9961234

Sheet RSI
A1: RSI: método de clase (promedios simples) y método de Wilder
B3: Periodo RSI | C3: 14 | E3: Comprobación de clase: con RS = | F3: 3.6 | G3: RSI = 100 - 100/(1+RS) = | H3: =100-100/(1+F3) -> 78.26087
E4: Zonas: > 70 sobrecompra, < 30 sobreventa, 30 a 70 equilibrio.
A8: t | B8: Fecha | C8: Cierre | D8: Cambio | E8: Ganancia | F8: Pérdida | G8: Prom. ganancia (simple) | H8: Prom. pérdida (simple) | I8: RS (simple) | J8: RSI (simple) | K8: Prom. ganancia (Wilder) | L8: Prom. pérdida (Wilder) | M8: RSI (Wilder) | N8: Zona (Wilder)
A9: =ROW()-8 -> 1 | B9: =Datos!A2 -> 45555 | C9: =Datos!B2 -> 167.72 | D9: =IF(A9=1,"",C9-C8) | E9: =IF(D9="","",MAX(D9,0)) | F9: =IF(D9="","",MAX(-D9,0)) | G9: =IF(A9<N_rsi+1,"",AVERAGE(INDEX($E$9:$E$112,A9-N_rsi+1):E9)) | H9: =IF(A9<N_rsi+1,"",AVERAGE(INDEX($F$9:$F$112,A9-N_rsi+1):F9)) | I9: =IF(G9="","",IF(H9=0,"sin pérdidas",G9/H9)) | J9: =IF(G9="","",IF(G9+H9=0,50,100*G9/(G9+H9))) | K9: =IF(A9<N_rsi+1,"",IF(A9=N_rsi+1,AVERAGE($E$9:E9),((N_rsi-1)*K8+E9)/N_rsi)) | L9: =IF(A9<N_rsi+1,"",IF(A9=N_rsi+1,AVERAGE($F$9:F9),((N_rsi-1)*L8+F9)/N_rsi)) | M9: =IF(K9="","",IF(K9+L9=0,50,100*K9/(K9+L9))) | N9: =IF(M9="","",IF(M9>70,"Sobrecompra",IF(M9<30,"Sobreventa","Equilibrio")))
A10: =ROW()-8 -> 2 | B10: =Datos!A3 -> 45562 | C10: =Datos!B3 -> 172.28 | D10: =IF(A10=1,"",C10-C9) -> 4.56 | E10: =IF(D10="","",MAX(D10,0)) -> 4.56 | F10: =IF(D10="","",MAX(-D10,0)) -> 0 | G10: =IF(A10<N_rsi+1,"",AVERAGE(INDEX($E$9:$E$112,A10-N_rsi+1):E10)) | H10: =IF(A10<N_rsi+1,"",AVERAGE(INDEX($F$9:$F$112,A10-N_rsi+1):F10)) | I10: =IF(G10="","",IF(H10=0,"sin pérdidas",G10/H10)) | J10: =IF(G10="","",IF(G10+H10=0,50,100*G10/(G10+H10))) | K10: =IF(A10<N_rsi+1,"",IF(A10=N_rsi+1,AVERAGE($E$9:E10),((N_rsi-1)*K9+E10)/N_rsi)) | L10: =IF(A10<N_rsi+1,"",IF(A10=N_rsi+1,AVERAGE($F$9:F10),((N_rsi-1)*L9+F10)/N_rsi)) | M10: =IF(K10="","",IF(K10+L10=0,50,100*K10/(K10+L10))) | N10: =IF(M10="","",IF(M10>70,"Sobrecompra",IF(M10<30,"Sobreventa","Equilibrio")))
A11: =ROW()-8 -> 3 | B11: =Datos!A4 -> 45569 | C11: =Datos!B4 -> 167.83 | D11: =IF(A11=1,"",C11-C10) -> -4.45 | E11: =IF(D11="","",MAX(D11,0)) -> 0 | F11: =IF(D11="","",MAX(-D11,0)) -> 4.45 | G11: =IF(A11<N_rsi+1,"",AVERAGE(INDEX($E$9:$E$112,A11-N_rsi+1):E11)) | H11: =IF(A11<N_rsi+1,"",AVERAGE(INDEX($F$9:$F$112,A11-N_rsi+1):F11)) | I11: =IF(G11="","",IF(H11=0,"sin pérdidas",G11/H11)) | J11: =IF(G11="","",IF(G11+H11=0,50,100*G11/(G11+H11))) | K11: =IF(A11<N_rsi+1,"",IF(A11=N_rsi+1,AVERAGE($E$9:E11),((N_rsi-1)*K10+E11)/N_rsi)) | L11: =IF(A11<N_rsi+1,"",IF(A11=N_rsi+1,AVERAGE($F$9:F11),((N_rsi-1)*L10+F11)/N_rsi)) | M11: =IF(K11="","",IF(K11+L11=0,50,100*K11/(K11+L11))) | N11: =IF(M11="","",IF(M11>70,"Sobrecompra",IF(M11<30,"Sobreventa","Equilibrio")))
A12: =ROW()-8 -> 4 | B12: =Datos!A5 -> 45576 | C12: =Datos!B5 -> 165.21 | D12: =IF(A12=1,"",C12-C11) -> -2.62 | E12: =IF(D12="","",MAX(D12,0)) -> 0 | F12: =IF(D12="","",MAX(-D12,0)) -> 2.62 | G12: =IF(A12<N_rsi+1,"",AVERAGE(INDEX($E$9:$E$112,A12-N_rsi+1):E12)) | H12: =IF(A12<N_rsi+1,"",AVERAGE(INDEX($F$9:$F$112,A12-N_rsi+1):F12)) | I12: =IF(G12="","",IF(H12=0,"sin pérdidas",G12/H12)) | J12: =IF(G12="","",IF(G12+H12=0,50,100*G12/(G12+H12))) | K12: =IF(A12<N_rsi+1,"",IF(A12=N_rsi+1,AVERAGE($E$9:E12),((N_rsi-1)*K11+E12)/N_rsi)) | L12: =IF(A12<N_rsi+1,"",IF(A12=N_rsi+1,AVERAGE($F$9:F12),((N_rsi-1)*L11+F12)/N_rsi)) | M12: =IF(K12="","",IF(K12+L12=0,50,100*K12/(K12+L12))) | N12: =IF(M12="","",IF(M12>70,"Sobrecompra",IF(M12<30,"Sobreventa","Equilibrio")))
A13: =ROW()-8 -> 5 | B13: =Datos!A6 -> 45583 | C13: =Datos!B6 -> 162.76 | D13: =IF(A13=1,"",C13-C12) -> -2.45 | E13: =IF(D13="","",MAX(D13,0)) -> 0 | F13: =IF(D13="","",MAX(-D13,0)) -> 2.45 | G13: =IF(A13<N_rsi+1,"",AVERAGE(INDEX($E$9:$E$112,A13-N_rsi+1):E13)) | H13: =IF(A13<N_rsi+1,"",AVERAGE(INDEX($F$9:$F$112,A13-N_rsi+1):F13)) | I13: =IF(G13="","",IF(H13=0,"sin pérdidas",G13/H13)) | J13: =IF(G13="","",IF(G13+H13=0,50,100*G13/(G13+H13))) | K13: =IF(A13<N_rsi+1,"",IF(A13=N_rsi+1,AVERAGE($E$9:E13),((N_rsi-1)*K12+E13)/N_rsi)) | L13: =IF(A13<N_rsi+1,"",IF(A13=N_rsi+1,AVERAGE($F$9:F13),((N_rsi-1)*L12+F13)/N_rsi)) | M13: =IF(K13="","",IF(K13+L13=0,50,100*K13/(K13+L13))) | N13: =IF(M13="","",IF(M13>70,"Sobrecompra",IF(M13<30,"Sobreventa","Equilibrio")))
A14: =ROW()-8 -> 6 | B14: =Datos!A7 -> 45590 | C14: =Datos!B7 -> 165.13 | D14: =IF(A14=1,"",C14-C13) -> 2.37 | E14: =IF(D14="","",MAX(D14,0)) -> 2.37 | F14: =IF(D14="","",MAX(-D14,0)) -> 0 | G14: =IF(A14<N_rsi+1,"",AVERAGE(INDEX($E$9:$E$112,A14-N_rsi+1):E14)) | H14: =IF(A14<N_rsi+1,"",AVERAGE(INDEX($F$9:$F$112,A14-N_rsi+1):F14)) | I14: =IF(G14="","",IF(H14=0,"sin pérdidas",G14/H14)) | J14: =IF(G14="","",IF(G14+H14=0,50,100*G14/(G14+H14))) | K14: =IF(A14<N_rsi+1,"",IF(A14=N_rsi+1,AVERAGE($E$9:E14),((N_rsi-1)*K13+E14)/N_rsi)) | L14: =IF(A14<N_rsi+1,"",IF(A14=N_rsi+1,AVERAGE($F$9:F14),((N_rsi-1)*L13+F14)/N_rsi)) | M14: =IF(K14="","",IF(K14+L14=0,50,100*K14/(K14+L14))) | N14: =IF(M14="","",IF(M14>70,"Sobrecompra",IF(M14<30,"Sobreventa","Equilibrio")))
A15: =ROW()-8 -> 7 | B15: =Datos!A8 -> 45597 | C15: =Datos!B8 -> 165.35 | D15: =IF(A15=1,"",C15-C14) -> 0.22 | E15: =IF(D15="","",MAX(D15,0)) -> 0.22 | F15: =IF(D15="","",MAX(-D15,0)) -> 0 | G15: =IF(A15<N_rsi+1,"",AVERAGE(INDEX($E$9:$E$112,A15-N_rsi+1):E15)) | H15: =IF(A15<N_rsi+1,"",AVERAGE(INDEX($F$9:$F$112,A15-N_rsi+1):F15)) | I15: =IF(G15="","",IF(H15=0,"sin pérdidas",G15/H15)) | J15: =IF(G15="","",IF(G15+H15=0,50,100*G15/(G15+H15))) | K15: =IF(A15<N_rsi+1,"",IF(A15=N_rsi+1,AVERAGE($E$9:E15),((N_rsi-1)*K14+E15)/N_rsi)) | L15: =IF(A15<N_rsi+1,"",IF(A15=N_rsi+1,AVERAGE($F$9:F15),((N_rsi-1)*L14+F15)/N_rsi)) | M15: =IF(K15="","",IF(K15+L15=0,50,100*K15/(K15+L15))) | N15: =IF(M15="","",IF(M15>70,"Sobrecompra",IF(M15<30,"Sobreventa","Equilibrio")))
A16: =ROW()-8 -> 8 | B16: =Datos!A9 -> 45604 | C16: =Datos!B9 -> 161.85 | D16: =IF(A16=1,"",C16-C15) -> -3.5 | E16: =IF(D16="","",MAX(D16,0)) -> 0 | F16: =IF(D16="","",MAX(-D16,0)) -> 3.5 | G16: =IF(A16<N_rsi+1,"",AVERAGE(INDEX($E$9:$E$112,A16-N_rsi+1):E16)) | H16: =IF(A16<N_rsi+1,"",AVERAGE(INDEX($F$9:$F$112,A16-N_rsi+1):F16)) | I16: =IF(G16="","",IF(H16=0,"sin pérdidas",G16/H16)) | J16: =IF(G16="","",IF(G16+H16=0,50,100*G16/(G16+H16))) | K16: =IF(A16<N_rsi+1,"",IF(A16=N_rsi+1,AVERAGE($E$9:E16),((N_rsi-1)*K15+E16)/N_rsi)) | L16: =IF(A16<N_rsi+1,"",IF(A16=N_rsi+1,AVERAGE($F$9:F16),((N_rsi-1)*L15+F16)/N_rsi)) | M16: =IF(K16="","",IF(K16+L16=0,50,100*K16/(K16+L16))) | N16: =IF(M16="","",IF(M16>70,"Sobrecompra",IF(M16<30,"Sobreventa","Equilibrio")))
A17: =ROW()-8 -> 9 | B17: =Datos!A10 -> 45611 | C17: =Datos!B10 -> 165.48 | D17: =IF(A17=1,"",C17-C16) -> 3.63 | E17: =IF(D17="","",MAX(D17,0)) -> 3.63 | F17: =IF(D17="","",MAX(-D17,0)) -> 0 | G17: =IF(A17<N_rsi+1,"",AVERAGE(INDEX($E$9:$E$112,A17-N_rsi+1):E17)) | H17: =IF(A17<N_rsi+1,"",AVERAGE(INDEX($F$9:$F$112,A17-N_rsi+1):F17)) | I17: =IF(G17="","",IF(H17=0,"sin pérdidas",G17/H17)) | J17: =IF(G17="","",IF(G17+H17=0,50,100*G17/(G17+H17))) | K17: =IF(A17<N_rsi+1,"",IF(A17=N_rsi+1,AVERAGE($E$9:E17),((N_rsi-1)*K16+E17)/N_rsi)) | L17: =IF(A17<N_rsi+1,"",IF(A17=N_rsi+1,AVERAGE($F$9:F17),((N_rsi-1)*L16+F17)/N_rsi)) | M17: =IF(K17="","",IF(K17+L17=0,50,100*K17/(K17+L17))) | N17: =IF(M17="","",IF(M17>70,"Sobrecompra",IF(M17<30,"Sobreventa","Equilibrio")))
A18: =ROW()-8 -> 10 | B18: =Datos!A11 -> 45618 | C18: =Datos!B11 -> 162.15 | D18: =IF(A18=1,"",C18-C17) -> -3.33 | E18: =IF(D18="","",MAX(D18,0)) -> 0 | F18: =IF(D18="","",MAX(-D18,0)) -> 3.33 | G18: =IF(A18<N_rsi+1,"",AVERAGE(INDEX($E$9:$E$112,A18-N_rsi+1):E18)) | H18: =IF(A18<N_rsi+1,"",AVERAGE(INDEX($F$9:$F$112,A18-N_rsi+1):F18)) | I18: =IF(G18="","",IF(H18=0,"sin pérdidas",G18/H18)) | J18: =IF(G18="","",IF(G18+H18=0,50,100*G18/(G18+H18))) | K18: =IF(A18<N_rsi+1,"",IF(A18=N_rsi+1,AVERAGE($E$9:E18),((N_rsi-1)*K17+E18)/N_rsi)) | L18: =IF(A18<N_rsi+1,"",IF(A18=N_rsi+1,AVERAGE($F$9:F18),((N_rsi-1)*L17+F18)/N_rsi)) | M18: =IF(K18="","",IF(K18+L18=0,50,100*K18/(K18+L18))) | N18: =IF(M18="","",IF(M18>70,"Sobrecompra",IF(M18<30,"Sobreventa","Equilibrio")))
A19: =ROW()-8 -> 11 | B19: =Datos!A12 -> 45625 | C19: =Datos!B12 -> 166.72 | D19: =IF(A19=1,"",C19-C18) -> 4.57 | E19: =IF(D19="","",MAX(D19,0)) -> 4.57 | F19: =IF(D19="","",MAX(-D19,0)) -> 0 | G19: =IF(A19<N_rsi+1,"",AVERAGE(INDEX($E$9:$E$112,A19-N_rsi+1):E19)) | H19: =IF(A19<N_rsi+1,"",AVERAGE(INDEX($F$9:$F$112,A19-N_rsi+1):F19)) | I19: =IF(G19="","",IF(H19=0,"sin pérdidas",G19/H19)) | J19: =IF(G19="","",IF(G19+H19=0,50,100*G19/(G19+H19))) | K19: =IF(A19<N_rsi+1,"",IF(A19=N_rsi+1,AVERAGE($E$9:E19),((N_rsi-1)*K18+E19)/N_rsi)) | L19: =IF(A19<N_rsi+1,"",IF(A19=N_rsi+1,AVERAGE($F$9:F19),((N_rsi-1)*L18+F19)/N_rsi)) | M19: =IF(K19="","",IF(K19+L19=0,50,100*K19/(K19+L19))) | N19: =IF(M19="","",IF(M19>70,"Sobrecompra",IF(M19<30,"Sobreventa","Equilibrio")))
A20: =ROW()-8 -> 12 | B20: =Datos!A13 -> 45632 | C20: =Datos!B13 -> 162.27 | D20: =IF(A20=1,"",C20-C19) -> -4.45 | E20: =IF(D20="","",MAX(D20,0)) -> 0 | F20: =IF(D20="","",MAX(-D20,0)) -> 4.45 | G20: =IF(A20<N_rsi+1,"",AVERAGE(INDEX($E$9:$E$112,A20-N_rsi+1):E20)) | H20: =IF(A20<N_rsi+1,"",AVERAGE(INDEX($F$9:$F$112,A20-N_rsi+1):F20)) | I20: =IF(G20="","",IF(H20=0,"sin pérdidas",G20/H20)) | J20: =IF(G20="","",IF(G20+H20=0,50,100*G20/(G20+H20))) | K20: =IF(A20<N_rsi+1,"",IF(A20=N_rsi+1,AVERAGE($E$9:E20),((N_rsi-1)*K19+E20)/N_rsi)) | L20: =IF(A20<N_rsi+1,"",IF(A20=N_rsi+1,AVERAGE($F$9:F20),((N_rsi-1)*L19+F20)/N_rsi)) | M20: =IF(K20="","",IF(K20+L20=0,50,100*K20/(K20+L20))) | N20: =IF(M20="","",IF(M20>70,"Sobrecompra",IF(M20<30,"Sobreventa","Equilibrio")))
... A112: =ROW()-8 -> 104 | B112: =Datos!A105 -> 46276 | C112: =Datos!B105 -> 218.77 | D112: =IF(A112=1,"",C112-C111) -> 4.6 | E112: =IF(D112="","",MAX(D112,0)) -> 4.6 | F112: =IF(D112="","",MAX(-D112,0)) -> 0 | G112: =IF(A112<N_rsi+1,"",AVERAGE(INDEX($E$9:$E$112,A112-N_rsi+1):E112)) -> 1.91 | H112: =IF(A112<N_rsi+1,"",AVERAGE(INDEX($F$9:$F$112,A112-N_rsi+1):F112)) -> 2.8771429 | I112: =IF(G112="","",IF(H112=0,"sin pérdidas",G112/H112)) -> 0.66385303 | J112: =IF(G112="","",IF(G112+H112=0,50,100*G112/(G112+H112))) -> 39.898538 | K112: =IF(A112<N_rsi+1,"",IF(A112=N_rsi+1,AVERAGE($E$9:E112),((N_rsi-1)*K111+E112)/N_rsi)) -> 2.636262 | L112: =IF(A112<N_rsi+1,"",IF(A112=N_rsi+1,AVERAGE($F$9:F112),((N_rsi-1)*L111+F112)/N_rsi)) -> 2.5891162 | M112: =IF(K112="","",IF(K112+L112=0,50,100*K112/(K112+L112))) -> 50.451123 | N112: =IF(M112="","",IF(M112>70,"Sobrecompra",IF(M112<30,"Sobreventa","Equilibrio"))) -> Equilibrio

Sheet Ejemplo_a_mano
A1: MACD(3, 6, 3) a mano sobre 12 precios
A2: Mismas fórmulas que MACD_EMA con periodos cortos para poder verificar cada celda con calculadora. alfa(3) = 0.5 ; alfa(6) = 2/7.
B4: Rápida | C4: Lenta | D4: Señal
A5: N | B5: 3 | C5: 6 | D5: 3
A6: alfa | B6: =2/(B5+1) -> 0.5 | C6: =2/(C5+1) -> 0.28571429 | D6: =2/(D5+1) -> 0.5
A8: t | B8: Cierre | C8: EMA 3 | D8: EMA 6 | E8: MACD | F8: Señal 3 | G8: Histograma
A9: 1 | B9: 10 | C9: =IF(A9<$B$5,"",IF(A9=$B$5,AVERAGE($B$9:B9),$B$6*B9+(1-$B$6)*C8)) | D9: =IF(A9<$C$5,"",IF(A9=$C$5,AVERAGE($B$9:B9),$C$6*B9+(1-$C$6)*D8)) | E9: =IF(D9="","",C9-D9) | F9: =IF(A9<$C$5+$D$5-1,"",IF(A9=$C$5+$D$5-1,AVERAGE($E$9:E9),$D$6*E9+(1-$D$6)*F8)) | G9: =IF(F9="","",E9-F9) | I9: Valores esperados (calculados con macd_toolkit.py):
A10: 2 | B10: 11 | C10: =IF(A10<$B$5,"",IF(A10=$B$5,AVERAGE($B$9:B10),$B$6*B10+(1-$B$6)*C9)) | D10: =IF(A10<$C$5,"",IF(A10=$C$5,AVERAGE($B$9:B10),$C$6*B10+(1-$C$6)*D9)) | E10: =IF(D10="","",C10-D10) | F10: =IF(A10<$C$5+$D$5-1,"",IF(A10=$C$5+$D$5-1,AVERAGE($E$9:E10),$D$6*E10+(1-$D$6)*F9)) | G10: =IF(F10="","",E10-F10) | I10: t=6: EMA6 = 11.8333, MACD = 1.1667
A11: 3 | B11: 12 | C11: =IF(A11<$B$5,"",IF(A11=$B$5,AVERAGE($B$9:B11),$B$6*B11+(1-$B$6)*C10)) -> 11 | D11: =IF(A11<$C$5,"",IF(A11=$C$5,AVERAGE($B$9:B11),$C$6*B11+(1-$C$6)*D10)) | E11: =IF(D11="","",C11-D11) | F11: =IF(A11<$C$5+$D$5-1,"",IF(A11=$C$5+$D$5-1,AVERAGE($E$9:E11),$D$6*E11+(1-$D$6)*F10)) | G11: =IF(F11="","",E11-F11) | I11: t=8: Señal = 1.0079 (promedio de los MACD de t=6,7,8), Histograma = 0.0159
A12: 4 | B12: 11 | C12: =IF(A12<$B$5,"",IF(A12=$B$5,AVERAGE($B$9:B12),$B$6*B12+(1-$B$6)*C11)) -> 11 | D12: =IF(A12<$C$5,"",IF(A12=$C$5,AVERAGE($B$9:B12),$C$6*B12+(1-$C$6)*D11)) | E12: =IF(D12="","",C12-D12) | F12: =IF(A12<$C$5+$D$5-1,"",IF(A12=$C$5+$D$5-1,AVERAGE($E$9:E12),$D$6*E12+(1-$D$6)*F11)) | G12: =IF(F12="","",E12-F12) | I12: t=12: MACD = 0.3768, Señal = 0.5218, Histograma = -0.1450
A13: 5 | B13: 13 | C13: =IF(A13<$B$5,"",IF(A13=$B$5,AVERAGE($B$9:B13),$B$6*B13+(1-$B$6)*C12)) -> 12 | D13: =IF(A13<$C$5,"",IF(A13=$C$5,AVERAGE($B$9:B13),$C$6*B13+(1-$C$6)*D12)) | E13: =IF(D13="","",C13-D13) | F13: =IF(A13<$C$5+$D$5-1,"",IF(A13=$C$5+$D$5-1,AVERAGE($E$9:E13),$D$6*E13+(1-$D$6)*F12)) | G13: =IF(F13="","",E13-F13)
A14: 6 | B14: 14 | C14: =IF(A14<$B$5,"",IF(A14=$B$5,AVERAGE($B$9:B14),$B$6*B14+(1-$B$6)*C13)) -> 13 | D14: =IF(A14<$C$5,"",IF(A14=$C$5,AVERAGE($B$9:B14),$C$6*B14+(1-$C$6)*D13)) -> 11.833333 | E14: =IF(D14="","",C14-D14) -> 1.1666667 | F14: =IF(A14<$C$5+$D$5-1,"",IF(A14=$C$5+$D$5-1,AVERAGE($E$9:E14),$D$6*E14+(1-$D$6)*F13)) | G14: =IF(F14="","",E14-F14)
A15: 7 | B15: 13 | C15: =IF(A15<$B$5,"",IF(A15=$B$5,AVERAGE($B$9:B15),$B$6*B15+(1-$B$6)*C14)) -> 13 | D15: =IF(A15<$C$5,"",IF(A15=$C$5,AVERAGE($B$9:B15),$C$6*B15+(1-$C$6)*D14)) -> 12.166667 | E15: =IF(D15="","",C15-D15) -> 0.83333333 | F15: =IF(A15<$C$5+$D$5-1,"",IF(A15=$C$5+$D$5-1,AVERAGE($E$9:E15),$D$6*E15+(1-$D$6)*F14)) | G15: =IF(F15="","",E15-F15)
A16: 8 | B16: 15 | C16: =IF(A16<$B$5,"",IF(A16=$B$5,AVERAGE($B$9:B16),$B$6*B16+(1-$B$6)*C15)) -> 14 | D16: =IF(A16<$C$5,"",IF(A16=$C$5,AVERAGE($B$9:B16),$C$6*B16+(1-$C$6)*D15)) -> 12.97619 | E16: =IF(D16="","",C16-D16) -> 1.0238095 | F16: =IF(A16<$C$5+$D$5-1,"",IF(A16=$C$5+$D$5-1,AVERAGE($E$9:E16),$D$6*E16+(1-$D$6)*F15)) -> 1.0079365 | G16: =IF(F16="","",E16-F16) -> 0.015873016
A17: 9 | B17: 16 | C17: =IF(A17<$B$5,"",IF(A17=$B$5,AVERAGE($B$9:B17),$B$6*B17+(1-$B$6)*C16)) -> 15 | D17: =IF(A17<$C$5,"",IF(A17=$C$5,AVERAGE($B$9:B17),$C$6*B17+(1-$C$6)*D16)) -> 13.840136 | E17: =IF(D17="","",C17-D17) -> 1.1598639 | F17: =IF(A17<$C$5+$D$5-1,"",IF(A17=$C$5+$D$5-1,AVERAGE($E$9:E17),$D$6*E17+(1-$D$6)*F16)) -> 1.0839002 | G17: =IF(F17="","",E17-F17) -> 0.075963719
A18: 10 | B18: 15 | C18: =IF(A18<$B$5,"",IF(A18=$B$5,AVERAGE($B$9:B18),$B$6*B18+(1-$B$6)*C17)) -> 15 | D18: =IF(A18<$C$5,"",IF(A18=$C$5,AVERAGE($B$9:B18),$C$6*B18+(1-$C$6)*D17)) -> 14.171526 | E18: =IF(D18="","",C18-D18) -> 0.82847425 | F18: =IF(A18<$C$5+$D$5-1,"",IF(A18=$C$5+$D$5-1,AVERAGE($E$9:E18),$D$6*E18+(1-$D$6)*F17)) -> 0.95618724 | G18: =IF(F18="","",E18-F18) -> -0.12771299
A19: 11 | B19: 14 | C19: =IF(A19<$B$5,"",IF(A19=$B$5,AVERAGE($B$9:B19),$B$6*B19+(1-$B$6)*C18)) -> 14.5 | D19: =IF(A19<$C$5,"",IF(A19=$C$5,AVERAGE($B$9:B19),$C$6*B19+(1-$C$6)*D18)) -> 14.122518 | E19: =IF(D19="","",C19-D19) -> 0.3774816 | F19: =IF(A19<$C$5+$D$5-1,"",IF(A19=$C$5+$D$5-1,AVERAGE($E$9:E19),$D$6*E19+(1-$D$6)*F18)) -> 0.66683442 | G19: =IF(F19="","",E19-F19) -> -0.28935282
A20: 12 | B20: 15 | C20: =IF(A20<$B$5,"",IF(A20=$B$5,AVERAGE($B$9:B20),$B$6*B20+(1-$B$6)*C19)) -> 14.75 | D20: =IF(A20<$C$5,"",IF(A20=$C$5,AVERAGE($B$9:B20),$C$6*B20+(1-$C$6)*D19)) -> 14.373227 | E20: =IF(D20="","",C20-D20) -> 0.37677257 | F20: =IF(A20<$C$5+$D$5-1,"",IF(A20=$C$5+$D$5-1,AVERAGE($E$9:E20),$D$6*E20+(1-$D$6)*F19)) -> 0.5218035 | G20: =IF(F20="","",E20-F20) -> -0.14503092

Sheet Graficas
A1: Últimos 26 periodos de MACD_EMA (filas 87 a 112)
A2: Si cambias el número de filas, actualiza los rangos: clic derecho en la gráfica > Seleccionar datos. Si el eje de precio arranca en 0, ajusta el mínimo en Dar formato al eje.
